{
  "schemaVersion": "1.0",
  "templates": [
    {
      "id": "tpl-saas-explainer-pscta-60",
      "name": "SaaS Product Explainer (60s)",
      "category": "explainer_educational",
      "use_case": "saas_product_explainer",
      "structure": "ps_cta",
      "path": "explainer_educational/saas_product_explainer.json",
      "platform": "youtube",
      "orientation": "16:9",
      "duration": 60,
      "tone": "professional",
      "tags": ["b2b", "product", "explainer"]
    },
    {
      "id": "tpl-bts-showcase-hvcta-30",
      "name": "Behind-the-Scenes Showcase (30s)",
      "category": "short_form_social",
      "use_case": "behind_the_scenes",
      "structure": "hv_cta",
      "path": "short_form_social/behind_the_scenes.json",
      "platform": "tiktok",
      "orientation": "9:16",
      "duration": 30,
      "tone": "friendly",
      "tags": ["social", "story", "authentic"]
    },
    {
      "id": "tpl-feature-update-pscta-30",
      "name": "Feature Update Spotlight (30s)",
      "category": "explainer_educational",
      "use_case": "feature_update_spotlight",
      "structure": "ps_cta",
      "path": "explainer_educational/feature_update_30.json",
      "platform": "youtube",
      "orientation": "16:9",
      "duration": 30,
      "tone": "professional",
      "tags": ["product","update","announcement"]
    },
    {
      "id": "tpl-ugc-review-hvcta-30",
      "name": "UGC Product Review (30s)",
      "category": "short_form_social",
      "use_case": "ugc_product_review",
      "structure": "hv_cta",
      "path": "short_form_social/ugc_review_30.json",
      "platform": "tiktok",
      "orientation": "9:16",
      "duration": 30,
      "tone": "friendly",
      "tags": ["ugc","review","authentic"]
    },
    {
      "id": "tpl-launch-teaser-pscta-15",
      "name": "Launch Teaser (15s)",
      "category": "marketing_promotional",
      "use_case": "launch_teaser",
      "structure": "ps_cta",
      "path": "marketing_promotional/launch_teaser_15.json",
      "platform": "instagram",
      "orientation": "9:16",
      "duration": 15,
      "tone": "inspirational",
      "tags": ["teaser","launch","promo"]
    },
    {
      "id": "tpl-event-recap-threeact-60",
      "name": "Event Recap (60s)",
      "category": "marketing_promotional",
      "use_case": "event_recap",
      "structure": "three_act",
      "path": "marketing_promotional/event_recap_60.json",
      "platform": "web",
      "orientation": "16:9",
      "duration": 60,
      "tone": "inspirational",
      "tags": ["event","recap","hype"]
    },
    {
      "id": "tpl-corporate-overview-threeact-60",
      "name": "Corporate Overview (60s)",
      "category": "testimonial_brand",
      "use_case": "corporate_overview",
      "structure": "three_act",
      "path": "testimonial_brand/corporate_overview_60.json",
      "platform": "linkedin",
      "orientation": "16:9",
      "duration": 60,
      "tone": "professional",
      "tags": ["brand","about","mission"]
    },
    {
      "id": "tpl-onboarding-walkthrough-pscta-45",
      "name": "Onboarding Walkthrough (45s)",
      "category": "explainer_educational",
      "use_case": "onboarding_walkthrough",
      "structure": "ps_cta",
      "path": "explainer_educational/onboarding_walkthrough_45.json",
      "platform": "web",
      "orientation": "16:9",
      "duration": 45,
      "tone": "professional",
      "tags": ["onboarding","how-to","product"]
    },
    {
      "id": "tpl-film-threeact-drama-90",
      "name": "Three-Act Film Scene (90s)",
      "category": "film_scene",
      "use_case": "drama_three_act",
      "structure": "three_act",
      "path": "film_scene/three_act_drama_90.json",
      "platform": "web",
      "orientation": "16:9",
      "duration": 90,
      "tone": "serious",
      "tags": ["film","narrative","drama"]
    },
    {
      "id": "tpl-hvc-hook-15",
      "name": "Hook-Value-CTA (15s)",
      "category": "short_form_social",
      "use_case": "hook_value_cta_short",
      "structure": "hv_cta",
      "path": "short_form_social/hvc_hook_15.json",
      "platform": "tiktok",
      "orientation": "9:16",
      "duration": 15,
      "tone": "humorous",
      "tags": ["short","snappy","trend"]
    },
    {
      "id": "tpl-customer-story-threeact-45",
      "name": "Customer Story (45s)",
      "category": "testimonial_brand",
      "use_case": "customer_testimonial",
      "structure": "three_act",
      "path": "testimonial_brand/customer_story_45.json",
      "platform": "linkedin",
      "orientation": "16:9",
      "duration": 45,
      "tone": "inspirational",
      "tags": ["testimonial","case study"]
    },
    {
      "id": "tpl-product-commercial-pscta-30",
      "name": "Product Commercial (30s)",
      "category": "marketing_promotional",
      "use_case": "product_commercial",
      "structure": "ps_cta",
      "path": "marketing_promotional/product_commercial_30.json",
      "platform": "youtube",
      "orientation": "16:9",
      "duration": 30,
      "tone": "professional",
      "tags": ["commercial","product"]
    },
    {
      "id": "tpl-how-it-works-60",
      "name": "How It Works (60s)",
      "category": "explainer_educational",
      "use_case": "how_it_works",
      "structure": "ps_cta",
      "path": "explainer_educational/how_it_works_60.json",
      "platform": "web",
      "orientation": "16:9",
      "duration": 60,
      "tone": "professional",
      "tags": ["explainer","how-to"]
    },
    {
      "id": "tpl-bts-how-made-30",
      "name": "How It's Made BTS (30s)",
      "category": "short_form_social",
      "use_case": "bts_how_made",
      "structure": "hv_cta",
      "path": "short_form_social/bts_how_made_30.json",
      "platform": "instagram",
      "orientation": "9:16",
      "duration": 30,
      "tone": "friendly",
      "tags": ["bts","process"]
    },
    {
      "id": "tpl-founder-message-30",
      "name": "Founder Message (30s)",
      "category": "testimonial_brand",
      "use_case": "founder_message",
      "structure": "hv_cta",
      "path": "testimonial_brand/founder_message_30.json",
      "platform": "linkedin",
      "orientation": "16:9",
      "duration": 30,
      "tone": "inspirational",
      "tags": ["message","founder","brand"]
    }
  ]
}
